ts2ml/__init__.py
ts2ml/_modidx.py
ts2ml/core.py
ts2ml-1.0.1.dist-info/LICENSE
ts2ml-1.0.1.dist-info/METADATA
ts2ml-1.0.1.dist-info/WHEEL
ts2ml-1.0.1.dist-info/entry_points.txt
ts2ml-1.0.1.dist-info/top_level.txt
ts2ml-1.0.1.dist-info/RECORD
