Metadata-Version: 2.1
Name: ts2ml
Version: 1.0.1
Summary: Tools to Transform a Time Series into Features and Target a.k.a Supervised Learning
Home-page: https://github.com/joaopcnogueira/ts2ml
Author: João Nogueira
Author-email: joaopcnogueira@gmail.com
License: Apache Software License 2.0
Keywords: nbdev jupyter notebook python
Platform: UNKNOWN
Classifier: Development Status :: 4 - Beta
Classifier: Intended Audience :: Developers
Classifier: Natural Language :: English
Classifier: Programming Language :: Python :: 3.7
Classifier: Programming Language :: Python :: 3.8
Classifier: Programming Language :: Python :: 3.9
Classifier: Programming Language :: Python :: 3.10
Classifier: License :: OSI Approved :: Apache Software License
Requires-Python: >=3.7
License-File: LICENSE
Requires-Dist: fastcore
Requires-Dist: pandas
Requires-Dist: numpy
Requires-Dist: tqdm
Requires-Dist: scikit-learn
Provides-Extra: dev
Requires-Dist: jupyter ; extra == 'dev'
